tekcoopbank/__init__.py
tekcoopbank/accounts.py
tekcoopbank/bank.py
tekcoopbank/exchange_rate.py
tekcoopbank/ift.py
tekcoopbank/mpesa.py
tekcoopbank/pesalink.py
tekcoopbank/transactions.py
pytekcoopbank-0.2.0.dist-info/LICENSE
pytekcoopbank-0.2.0.dist-info/METADATA
pytekcoopbank-0.2.0.dist-info/WHEEL
pytekcoopbank-0.2.0.dist-info/entry_points.txt
pytekcoopbank-0.2.0.dist-info/top_level.txt
pytekcoopbank-0.2.0.dist-info/RECORD
